Workbook

Sheet Project Summary
A1: Project Summary | E1: Notes
A3: Project Name:
A5: Civic Address:
A7: Units
A9: GFA
A10: NFA
A12: Notes
B14: Yellow Tabs require inputs

Sheet Inputs & Assumptions
A1: Inputs & Assumptions
A3: BUILDING
A4: Site Area
A5: GFA | C5: ='Sales Detail'!F39 -> 3690
A6: NFA | C6: =C7*C5 -> 3690
A7: Efficiency | C7: 1
A8: Common | C8: =C5-C6 -> 0
A9: Units | B9: Residential | C9: 20
B10: CRU | C10: 4 | N10: 7287
B11: Total | C11: =C9+C10 -> 24 | N11: 611
A12: Lockers | C12: 25 | N12: 1168
A13: Parking | C13: 97 | D13: =C13/C11 -> 4.0416667 | N13: 2922
N14: 211
A15: CONSTRUCTION | N15: 8337
A16: Cost per Square metre | C16: 800 | N16: 6462
A17: Construction Cost | C17: =C16*C5 -> 2952000 | N17: =SUM(N10:N16) -> 26998
A18: Construction Contingency | C18: 0.05
A19: Construction Fee | C19: 0
A21: DEVELOPMENT
A22: Project Management Fee | C22: 0.05
A23: Marketing | C23: 0.005
A24: Insurance | C24: 0.015
A26: PRESALES
A27: Presales | C27: 0.65
A28: Deposit Amount | C28: 0.15
A29: sold in | C29: 20 | D29: months starting month of construction
A30: Commissions | C30: 0.05
A31: SALES
A32: Sale Price per sqr metre | C32: 1850
A34: FINANCIAL
A35: LP Preferred Return | C35: 0.08
A36: LP Waterfall | C36: 0.5

Sheet Development Proforma
A1: FIFTH AVENUE - PROFORMA
B2: PROJECT: | C2: Seseh Project | G2: TYPE: | H2: Residential/Retail
B3: ADDRESS: | C3: Seseh - Bali | G3: Project #: | H3: TBD
B5: SUMMARY OF PROFORMA
B6: SITE AREA (SF) | C6: ='Inputs & Assumptions'!C4 -> 0
B8: BUILDING AREA (SF) | E8: =C11/C14 -> 184.5
B9: - Net Floor Area (NFA) | C9: ='Inputs & Assumptions'!C6 -> 3690 | G9: Number of Floors: | H9: 2
B10: - Common Area/Hall Space | C10: ='Inputs & Assumptions'!C8 -> 0 | G10: Constrcution: | H10: Concrete
B11: - Gross Floor Area (GFA) | C11: ='Inputs & Assumptions'!C5 -> 3690 | G11: Building Efficiency | H11: ='Inputs & Assumptions'!C7 -> 1
B13: UNITS
B14: - Residential | C14: ='Inputs & Assumptions'!C9 -> 20
B15: DEVELOPMENT BUDGET
B17: LAND | G17: Cost Buildable/Gross sqft
C18: Land Cost | H18: 400000
C19: Property purchase taxes
C20: Rezone/Predevelopment Costs | H20: 0
C21: Legal Fees
C23: SUBTOTAL | I23: =SUM(H18:H21) -> 400000
B25: CONSTRUCTION COSTS | G25: Cost Buildable/Gross sqr metre
C26: Construction Contract - Base Contract | G26: ='Inputs & Assumptions'!C16 -> 800 | H26: =G26*'Inputs & Assumptions'!C5 -> 2952000 | I26: (RBD Bare construction risk)
C27: Construction Contingency | G27: 0 | H27: =H26*G27 -> 0 | I27: (Fixed Rate)
C29: SUBTOTAL | I29: =SUM(H26:H27) -> 2952000
B31: CASH ALLOWANCES
C33: SUBTOTAL | I33: =SUM(H31:H32) -> 0
B35: CONSULTANTS
C36: Architectural Fees & Consultants | G36: Included in Construction cost
C37: Permit and DCC | G37: Included In construction cost
C38: Other consultants
E39: Landscape Artictect
E40: Structural Engineering
E41: Mechanical Engineering
E42: Electrical Engineering
E43: Civil Engineering
E44: Code Consultant
C45: Geotechnical Engineering
C46: Survey Costs
C48: SUBTOTAL | I48: =SUM(H36:H46) -> 0
B50: MUNICIPAL
C51: Rezoning and Developemnt Permit Fees
C52: Building Permit fees (if not in construction)
C53: Other municipal fees
C55: SUBTOTAL | I55: =SUM(H51:H53) -> 0
B57: CONSULTING
C58: Project Management Fee | G58: ='Inputs & Assumptions'!C22 -> 0.05 | H58: =G58*H104 -> 321000
C59: Marketing | G59: 0.02 | H59: =G59*H104 -> 128400
C61: SUBTOTAL | I61: =SUM(H57:H59) -> 449400
B63: SUPPORT SERVICES | G63: Number of units | H63: Cost per unit | I63: Total Cost
C64: PT PMA SETUP | G64: =$C$14 -> 20 | H64: 800 | I64: =H64*G64 -> 16000
C65: Deed Amendment | G65: =$C$14 -> 20 | H65: 106.75 | I65: =H65*G65 -> 2135
C66: Villa Licensing | G66: =$C$14 -> 20 | H66: 111.17 | I66: =H66*G66 -> 2223.4
C67: NPWPD Registration | G67: =$C$14 -> 20 | H67: 385.4 | I67: =H67*G67 -> 7708
C68: Annual Legal Compliance | G68: =$C$14 -> 20 | H68: 427 | I68: =H68*G68 -> 8540
C69: Legal Due Diligence | G69: =$C$14 -> 20 | H69: 172.94 | I69: =H69*G69 -> 3458.8
C70: Notary Fees – 1% | G70: =$C$14 -> 20 | H70: 0 | I70: =H70*G70 -> 0
C72: SUBTOTAL | I72: =SUM(H64:H70)*C14 -> 40065.2
B74: Furnishing costs | G74: Number of units | H74: Cost per unit
C77: Furnitures | D77: 2 beds | G77: 10 | H77: 16000 | I77: =G77*H77 -> 160000
C78: Furnitures | D78: 3 beds | G78: 6 | H78: 25000 | I78: =H78*G78 -> 150000
C79: Furnitures | D79: 4 beds | G79: 4 | H79: 30000 | I79: =H79*G79 -> 120000
I86: =SUM(I77:I79) -> 430000
B88: PROJECT CONTINGENCY
G89: 0 | H89: =G89*I29 -> 0
C90: SUBTOTAL | I90: =H89 -> 0
B91: Capital Raise Fee | C91: 0.05 | I91: =I100*C91 -> 83284.59
B93: TOTAL PROJECT COSTS | I93: =I90+I86+I72+I61+I55+I48+I33+I29+I23+I91 -> 4354749.8
B95: CAPITAL STACK
B96: Pre Sales | H96: ='Inputs & Assumptions'!C27 -> 0.65 | I96: =I93*H96 -> 2830587.4 | K96: =12/20 -> 0.6
B97: Number of Pre sales (BC) | I97: =H96*C14 -> 13
B98: Pre Sales Revenue after coms | I98: ='Sales Detail'!K20 -> 2689058
B100: EQUITY REQUIRED FOR PROJECT | I100: =I93-I98 -> 1665691.8
B102: PROFITABILITY ANALYSIS
B103: SALES REVENUES
C104: Gross Revenue | H104: ='Sales Detail'!I39 -> 6420000
C105: Brokers Fees | D105: 0.05 | H105: =H104*D105 -> 321000
C106: Net Revenue | H106: =H104-H105 -> 6099000
B109: NET SALES | I109: =H106 -> 6099000
B111: TOTAL PROJECT COST | I111: =I93 -> 4354749.8
B113: PROJECTED PROFIT ON PROJECT | I113: =I109-I111 -> 1744250.2
B114: Return on Cost/ROI | I114: =I113/I111 -> 0.40053971
B115: Return on Equity | I115: =I113/I100 -> 1.0471626
B117: LP Preferred Return | C117: 0.08 | I117: =((I100*C117)/12)*'Inputs & Assumptions'!C29 -> 222092.24
B119: Profit for distribution | I119: =I113-I117 -> 1522158
B120: LP | C120: ='Inputs & Assumptions'!C36 -> 0.5 | I120: =I119*C120 -> 761078.99
B121: GP | C121: =1-C120 -> 0.5 | I121: =I119*C121 -> 761078.99
B123: Total LP Profit | I123: =I120+I117 -> 983171.22
B125: ROI | I125: =I123/I100 -> 0.59024798
B127: LP IRR over 20 months | I127: ='Cash Flow'!E99 -> 0.32173514

Sheet Cash Flow
A1: FIFTH AVENUE - CASHFLOW
B2: PROJECT: | C2: ='Development Proforma'!C2 -> Seseh Project | G2: TYPE: | H2: Residential
B3: ADDRESS: | C3: Coronation Ave, Kelowna | G3: Project #: | H3: ='Development Proforma'!H3 -> TBD
B5: ASSUMPTIONS
C6: Start Date: | D6: 46174
C7: Development Phase | D7: 11 | E7: months
C8: Construction Phase | D8: 12 | E8: months
J10: 0 | K10: 1 | L10: 2 | M10: 3 | N10: 4 | O10: 5 | P10: 6 | Q10: 7 | R10: 8 | S10: 9 | T10: 10 | U10: 11 | V10: 12 | W10: 13 | X10: 14 | Y10: 15 | Z10: 16 | AA10: 17 | AB10: 18 | AC10: 19 | AD10: 20 | AE10: 21 | AF10: 22 | AG10: 23 | AH10: 24 | AI10: 25 | AJ10: 26 | AK10: 27 | AL10: 28 | AM10: 29 | AN10: 30 | AO10: 31 | AP10: 32 | AQ10: 33 | AR10: 34 | AS10: 33 | AU10: Total | AW10: Check
J11: 46054 | K11: 46082 | L11: 46113 | M11: 46143 | N11: 46174 | O11: 46204 | P11: 46235 | Q11: 46266 | R11: 46296 | S11: 46327 | T11: 46357 | U11: 46388 | V11: 46419 | W11: 46447 | X11: 46478 | Y11: 46508 | Z11: 46539 | AA11: 46569 | AB11: 46600 | AC11: 46631 | AD11: 46661 | AE11: 46692 | AF11: 46722 | AG11: 46753 | AH11: 46784 | AI11: 46813 | AJ11: 46844 | AK11: 46874 | AL11: 46905 | AM11: 46935 | AN11: 46966 | AO11: 46997 | AP11: 47027 | AQ11: 47058 | AR11: 47088 | AS11: 47119
B12: COST SCHEDULE
B14: LAND
C15: ='Development Proforma'!C18 -> Land Cost | H15: ='Development Proforma'!H18 -> 400000 | M15: =H15 -> 400000 | AU15: =SUM(J15:AS15) -> 400000 | AW15: =IF(AU15=H15,"Y", "Error") -> Y
C16: Property purchase taxes | H16: ='Development Proforma'!H19 -> 0 | AU16: =SUM(J16:AS16) -> 0 | AW16: =IF(AU16=H16,"Y", "Error") -> Y
C17: Rezone/Predevelopment Costs | H17: ='Development Proforma'!H20 -> 0 | AU17: =SUM(J17:AS17) -> 0 | AW17: =IF(AU17=H17,"Y", "Error") -> Y
C18: Legal Fees | H18: ='Development Proforma'!H21 -> 0 | AU18: =SUM(J18:AS18) -> 0 | AW18: =IF(AU18=H18,"Y", "Error") -> Y
B19: CONSTRUCTION COSTS | AU19: =SUM(J19:AS19) -> 0
C20: Construction Contract - Base Contract | H20: ='Development Proforma'!H26 -> 2952000 | N20: =$H$20/$D$8 -> 246000 | O20: =$H$20/$D$8 -> 246000 | P20: =$H$20/$D$8 -> 246000 | Q20: =$H$20/$D$8 -> 246000 | R20: =$H$20/$D$8 -> 246000 | S20: =$H$20/$D$8 -> 246000 | T20: =$H$20/$D$8 -> 246000 | U20: =$H$20/$D$8 -> 246000 | ... Y20: =$H$20/$D$8 -> 246000 | AU20: =SUM(J20:AS20) -> 2952000 | AW20: =IF(AU20=H20,"Y", "Error") -> Y
AU21: =SUM(J21:AS21) -> 0 | AW21: =IF(AU21=H21,"Y", "Error") -> Y
C22: Architectural Fees | H22: ='Development Proforma'!H39 -> 0 | AU22: =SUM(J22:AS22) -> 0 | AW22: =IF(AU22=H22,"Y", "Error") -> Y
C23: Landscape Artictect | H23: ='Development Proforma'!H40 -> 0 | AU23: =SUM(J23:AS23) -> 0 | AW23: =IF(AU23=H23,"Y", "Error") -> Y
C24: Structural Engineering | H24: ='Development Proforma'!H41 -> 0 | AU24: =SUM(J24:AS24) -> 0 | AW24: =IF(AU24=H24,"Y", "Error") -> Y
C25: Mechanical Engineering | H25: ='Development Proforma'!H42 -> 0 | AU25: =SUM(J25:AS25) -> 0 | AW25: =IF(AU25=H25,"Y", "Error") -> Y
C26: Electrical Engineering | H26: ='Development Proforma'!H43 -> 0 | AU26: =SUM(J26:AS26) -> 0 | AW26: =IF(AU26=H26,"Y", "Error") -> Y
C27: Civil Engineering | H27: ='Development Proforma'!H44 -> 0 | AU27: =SUM(J27:AS27) -> 0 | AW27: =IF(AU27=H27,"Y", "Error") -> Y
C28: Code Consultant | H28: ='Development Proforma'!H45 -> 0 | AU28: =SUM(J28:AS28) -> 0 | AW28: =IF(AU28=H28,"Y", "Error") -> Y
C29: Geotechnical Engineering | H29: ='Development Proforma'!H46 -> 0 | AU29: =SUM(J29:AS29) -> 0 | AW29: =IF(AU29=H29,"Y", "Error") -> Y
C30: Survey Costs | H30: ='Development Proforma'!H46 -> 0 | AU30: =SUM(J30:AS30) -> 0 | AW30: =IF(AU30=H30,"Y", "Error") -> Y
B31: MUNICIPAL | AU31: =SUM(J31:AS31) -> 0 | AW31: =IF(AU31=H31,"Y", "Error") -> Y
C32: Rezoning and Developemnt Permit Fees | H32: ='Development Proforma'!H51 -> 0 | AU32: =SUM(J32:AS32) -> 0 | AW32: =IF(AU32=H32,"Y", "Error") -> Y
C33: Building Permit fees (if not in construction) | H33: ='Development Proforma'!H52 -> 0 | AU33: =SUM(J33:AS33) -> 0 | AW33: =IF(AU33=H33,"Y", "Error") -> Y
C34: Other municipal fees | H34: ='Development Proforma'!H53 -> 0 | AU34: =SUM(J34:AS34) -> 0 | AW34: =IF(AU34=H34,"Y", "Error") -> Y
B35: CONSULTING | AU35: =SUM(J35:AS35) -> 0
C36: Project Management Fee | H36: ='Development Proforma'!H58 -> 321000 | M36: =H36*0.5 -> 160500 | N36: =($H$36-$M$36)/12 -> 13375 | O36: =($H$36-$M$36)/12 -> 13375 | P36: =($H$36-$M$36)/12 -> 13375 | Q36: =($H$36-$M$36)/12 -> 13375 | R36: =($H$36-$M$36)/12 -> 13375 | S36: =($H$36-$M$36)/12 -> 13375 | T36: =($H$36-$M$36)/12 -> 13375 | U36: =($H$36-$M$36)/12 -> 13375 | ... Y36: =($H$36-$M$36)/12 -> 13375 | AU36: =SUM(J36:AS36) -> 321000 | AW36: =IF(AU36=H36,"Y", "Error") -> Y
C37: Marketing | H37: ='Development Proforma'!H59 -> 128400 | J37: =$H$37/17 -> 7552.9412 | K37: =$H$37/17 -> 7552.9412 | L37: =$H$37/17 -> 7552.9412 | M37: =$H$37/17 -> 7552.9412 | N37: =$H$37/17 -> 7552.9412 | O37: =$H$37/17 -> 7552.9412 | P37: =$H$37/17 -> 7552.9412 | Q37: =$H$37/17 -> 7552.9412 | ... Z37: =$H$37/17 -> 7552.9412 | AU37: =SUM(J37:AS37) -> 128400 | AW37: =IF(AU37=H37,"Y", "Error") -> Y
B38: SUPPORT SERVICES | AU38: =SUM(J38:AS38) -> 0
C39: PT PMA SETUP | AU39: =SUM(J39:AS39) -> 0 | AW39: =IF(AU39=H39,"Y", "Error") -> Y
C40: Deed Amendment | AU40: =SUM(J40:AS40) -> 0 | AW40: =IF(AU40=H40,"Y", "Error") -> Y
C41: Villa Licensing | AU41: =SUM(J41:AS41) -> 0 | AW41: =IF(AU41=H41,"Y", "Error") -> Y
C42: NPWPD Registration | AU42: =SUM(J42:AS42) -> 0 | AW42: =IF(AU42=H42,"Y", "Error") -> Y
C43: Annual Legal Compliance | AU43: =SUM(J43:AS43) -> 0 | AW43: =IF(AU43=H43,"Y", "Error") -> Y
C44: Legal Due Diligence | K44: ='Sales Detail'!N17*$G$44*0.5 -> 0 | L44: ='Sales Detail'!O17*$G$44*0.5 -> 0 | O44: ='Sales Detail'!P17*$G$44*0.5 -> 0 | P44: ='Sales Detail'!T17*$G$44*0.5 -> 0 | Q44: ='Sales Detail'!U17*$G$44*0.5 -> 0 | R44: ='Sales Detail'!V17*$G$44*0.5 -> 0 | S44: ='Sales Detail'!W17*$G$44*0.5 -> 0 | T44: ='Sales Detail'!X17*$G$44*0.5 -> 0 | U44: ='Sales Detail'!Y17*$G$44*0.5 -> 0 | Z44: ='Sales Detail'!Z17*$G$44*0.5 -> 0 | AA44: ='Sales Detail'!AA17*$G$44*0.5 -> 0 | AB44: ='Sales Detail'!AB17*$G$44*0.5 -> 0 | AC44: ='Sales Detail'!AC17*$G$44*0.5 -> 0 | AD44: ='Sales Detail'!AD17*$G$44*0.5 -> 0 | AE44: ='Sales Detail'!AE17*$G$44*0.5 -> 0 | AF44: ='Sales Detail'!AF17*$G$44*0.5 -> 0 | AG44: ='Sales Detail'!AG17*$G$44*0.5 -> 0 | ... AK44: ='Sales Detail'!AK17*$G$44*0.5 -> 0 | AL44: =H44-SUM(S44:AK44) -> 0 | AU44: =SUM(J44:AS44) -> 0 | AW44: =IF(AU44=H44,"Y", "Error") -> Y
AU45: =SUM(J45:AS45) -> 0 | AW45: =IF(AU45=H45,"Y", "Error") -> Y
C46: Total Legal Fee's | H46: ='Development Proforma'!I72 -> 40065.2 | J46: =H46 -> 40065.2 | AU46: =SUM(J46:AS46) -> 40065.2 | AW46: =IF(AU46=H46,"Y", "Error") -> Y
AU47: =SUM(J47:AS47) -> 0 | AW47: =IF(AU47=H47,"Y", "Error") -> Y
AU48: =SUM(J48:AS48) -> 0 | AW48: =IF(AU48=H48,"Y", "Error") -> Y
AU49: =SUM(J49:AS49) -> 0 | AW49: =IF(AU49=H49,"Y", "Error") -> Y
AU50: =SUM(J50:AS50) -> 0 | AW50: =IF(AU50=H50,"Y", "Error") -> Y
B51: Furniture | AU51: =SUM(J51:AS51) -> 0 | AW51: =IF(AU51=H51,"Y", "Error") -> Y
C52: Total Cost | H52: ='Development Proforma'!I86 -> 430000 | U52: =H52 -> 430000 | AU52: =SUM(J52:AS52) -> 430000 | AW52: =IF(AU52=H52,"Y", "Error") -> Y
B54: Capital Fees
C55: Capital Raise Fee | H55: ='Development Proforma'!I91 -> 83284.59 | J55: =H55 -> 83284.59
AU56: =SUM(J56:AS56) -> 0 | AW56: =IF(AU56=H56,"Y", "Error") -> Y
B57: TOTAL COSTS | H57: =H15+H20+H36+H37+H46+H52 -> 4271465.2 | J57: =SUM(J15:J56) -> 130902.73 | K57: =SUM(K15:K56) -> 7552.9412 | L57: =SUM(L15:L56) -> 7552.9412 | M57: =SUM(M15:M56) -> 568052.94 | N57: =SUM(N15:N56) -> 266927.94 | O57: =SUM(O15:O56) -> 266927.94 | P57: =SUM(P15:P56) -> 266927.94 | Q57: =SUM(Q15:Q56) -> 266927.94 | ... U57: =SUM(U15:U56) -> 696927.94 | V57: =SUM(V13:V56) -> 266927.94 | W57: =SUM(W15:W56) -> 266927.94 | X57: =SUM(X15:X56) -> 266927.94 | Y57: =SUM(Y15:Y56) -> 266927.94 | Z57: =SUM(Z15:Z56) -> 7552.9412 | AA57: =SUM(AA15:AA56) -> 0 | AB57: =SUM(AB15:AB56) -> 0 | AC57: =SUM(AC15:AC56) -> 0 | AD57: =SUM(AD15:AD56) -> 0 | ... AT57: =SUM(AT15:AT56) -> 0 | AU57: =SUM(J57:AS57) -> 4354749.8 | AW57: =IF(AU57=H57,"Y", "Error") -> Error
B60: SOURCE OF FUNDS
C61: Deposits/Sales Proceeds needed for Financing | H61: ='Development Proforma'!I98 -> 2689058 | M61: ='Sales Detail'!M20 -> 403358.7 | N61: ='Sales Detail'!N20 -> 268905.8 | O61: ='Sales Detail'!O20 -> 183344.86 | P61: ='Sales Detail'!P20 -> 183344.86 | Q61: ='Sales Detail'!Q20 -> 183344.86 | R61: ='Sales Detail'!R20 -> 183344.86 | S61: ='Sales Detail'!S20 -> 183344.86 | T61: ='Sales Detail'!T20 -> 183344.86 | ... Y61: ='Sales Detail'!Y20 -> 183344.86 | AK61: =AK68 -> 0 | AU61: =SUM(K61:AS61) -> 2689058 | AW61: =IF(AU61=H61,"Y", "Error") -> Y
C62: Residual Sales | H62: ='Development Proforma'!I109-'Development Proforma'!I98 -> 3409942 | AD62: =H62 -> 3409942
H63: =H61*-G63 -> 0 | AU63: =SUM(K63:AS63) -> 0 | AW63: =IF(AU63=H63,"Y", "Error") -> Y
C64: Final Sales | AN64: =-AN57-AO57 -> 0 | AU64: =SUM(K64:AS64) -> 0
C65: Project Cash Flow | E65: ='Development Proforma'!I100 -> 1665691.8 | H65: =E65 -> 1665691.8 | J65: =(E65-J57)+J61 -> 1534789.1 | K65: =(J65-K57)+K61 -> 1527236.1 | L65: =(K65-L57)+L61 -> 1519683.2 | M65: =(L65-M57)+M61 -> 1354988.9 | N65: =(M65-N57)+N61 -> 1356966.8 | O65: =(N65-O57)+O61 -> 1273383.7 | P65: =(O65-P57)+P61 -> 1189800.6 | Q65: =(P65-Q57)+Q61 -> 1106217.6 | R65: =(Q65-R57)+R61 -> 1022634.5 | ... Z65: =(Y65-Z57)+Z61 -> 7.1213435e-10 | AD65: =SUM(AD57:AD63) -> 3409942
AU66: =SUM(K66:AS66) -> 0 | AW66: =IF(AU66=#REF!,"Y", "Error") -> #REF!
C67: Equity | E67: =E65 -> 1665691.8 | AU67: =SUM(W67:AS67) -> 0 | AW67: =IF(AU67=#REF!,"Y", "Error") -> #REF!
AW68: =IF(AU68=H68,"Y", "Error") -> Y
AU69: =SUM(K69:AS69) -> 0 | AW69: =IF(AU69=H69,"Y", "Error") -> Y | AY69: Due to costs incurred after completion. Per the proforma these are part of the capital stack bnut in reality these are paid out of sales proceeds.
C71: LOAN ADVANCE AND INTEREST CALCULATION
C72: Net Draw | H72: =H69 -> 0 | K72: =K69 -> 0 | L72: =L69 -> 0 | O72: =O69 -> 0 | P72: =P69 -> 0 | Q72: =Q69 -> 0 | R72: =R69 -> 0 | S72: =S69 -> 0 | T72: =T69 -> 0 | U72: =U69 -> 0 | V72: =V69 -> 0 | ... AM72: =AM69 -> 0 | AN72: =-AM73 -> 0 | AO72: =AO69 -> 0 | AU72: =SUM(K72:AS72) -> 0 | AW72: =IF(AU72=0,"Y", "Error") -> Y | AY72: Due to costs incurred after completion. Per the proforma these are part of the capital stack bnut in reality these are paid out of sales proceeds.
C73: Cumulative Draw | K73: =I73+K72 -> 0 | L73: =K73+L72 -> 0 | O73: =L73+O72 -> 0 | P73: =O73+P72 -> 0 | Q73: =P73+Q72 -> 0 | R73: =Q73+R72 -> 0 | S73: =R73+S72 -> 0 | T73: =S73+T72 -> 0 | U73: =T73+U72 -> 0 | V73: =U73+V72 -> 0 | W73: =V73+W72 -> 0 | ... AO73: =AN73+AO72 -> 0
C74: Prime Rate
C75: Borrowing Rate @ prime + | H75: ='Inputs & Assumptions'!#REF! -> #REF! | K75: =$H$75 -> #REF! | L75: =$H$75 -> #REF! | M75: =$H$75 -> #REF! | N75: =$H$75 -> #REF! | O75: =$H$75 -> #REF! | P75: =$H$75 -> #REF! | Q75: =$H$75 -> #REF! | R75: =$H$75 -> #REF! | ... AO75: =$H$75 -> #REF!
C76: Cost of Construction Borrowing | H76: =#REF! -> #REF! | K76: =(K75*K73)/12 -> #REF! | L76: =(L75*L73)/12 -> #REF! | M76: =(M75*M73)/12 -> #REF! | N76: =(N75*N73)/12 -> #REF! | O76: =(O75*O73)/12 -> #REF! | P76: =(P75*P73)/12 -> #REF! | Q76: =(Q75*Q73)/12 -> #REF! | R76: =(R75*R73)/12 -> #REF! | ... AM76: =(AM75*AM73)/12 -> #REF! | AU76: =SUM(K76:AS76) -> #REF! | AW76: =IF(AU76=H76,"Y", "Error") -> #REF! | AY76: Not material (error from rounding on finance fees)
C78: Net Deposits | H78: =H68 -> 0 | K78: =K68 -> 0 | L78: =L68 -> 0 | M78: =M68 -> 0 | N78: =N68 -> 0 | O78: =O68 -> 0 | P78: =P68 -> 0 | Q78: =Q68 -> 0 | R78: =R68 -> 0 | ... AK78: =AK68 -> 0
C79: Cumulative Deposits | K79: =I79+K78 -> 0 | L79: =K79+L78 -> 0 | M79: =L79+M78 -> 0 | N79: =M79+N78 -> 0 | O79: =L79+O78 -> 0 | P79: =O79+P78 -> 0 | Q79: =P79+Q78 -> 0 | R79: =Q79+R78 -> 0 | S79: =R79+S78 -> 0 | T79: =S79+T78 -> 0 | U79: =T79+U78 -> 0 | V79: =U79+V78 -> 0 | W79: =V79+W78 -> 0 | ... AM79: =AL79+AM78 -> 0
C80: Insurance Rate | H80: ='Inputs & Assumptions'!#REF! -> #REF! | K80: =$H$80 -> #REF! | L80: =$H$80 -> #REF! | M80: =$H$80 -> #REF! | N80: =$H$80 -> #REF! | O80: =$H$80 -> #REF! | P80: =$H$80 -> #REF! | Q80: =$H$80 -> #REF! | R80: =$H$80 -> #REF! | ... AM80: =$H$80 -> #REF!
C81: Cost of Deposit Insurance | K81: =(K80*K79/12) -> #REF! | L81: =(L80*L79/12) -> #REF! | O81: =(O80*O79/12) -> #REF! | P81: =(P80*P79/12) -> #REF! | Q81: =(Q80*Q79/12) -> #REF! | R81: =(R80*R79/12) -> #REF! | S81: =(S80*S79/12) -> #REF! | T81: =(T80*T79/12) -> #REF! | U81: =(U80*U79/12) -> #REF! | V81: =(V80*V79/12) -> #REF! | ... AM81: =(AM80*AM79/12) -> #REF! | AU81: =SUM(K81:AS81) -> #REF!
B83: IRR CALCULATIONS
C85: Investor Cash Flows | D85: Equty and Repayment | M85: =-'Development Proforma'!I100 -> -1665691.8 | AC85: =-AC66 -> 0 | AD85: =-AD66 -> 0 | AE85: =-AE66 -> 0 | AF85: =-AF66 -> 0 | AG85: =-AG66 -> 0 | AH85: =-AH66 -> 0 | AI85: =-AI66 -> 0 | AJ85: =-AJ66 -> 0 | AK85: =-AK66 -> 0 | AM85: =-AM66 -> 0 | AN85: =-M85 -> 1665691.8
D86: LP Preferred Return | G86: 0.08 | AN86: =(AN85)*G86/12*(AN10-M10) -> 299824.52
D87: LP Fixed Return | G87: ='Inputs & Assumptions'!C36 -> 0.5 | AN87: ='Development Proforma'!I120 -> 761078.99
D88: Total | J88: =SUM(J85:J87) -> 0 | K88: =SUM(K85:K87) -> 0 | L88: =SUM(L85:L87) -> 0 | M88: =SUM(M85:M87) -> -1665691.8 | N88: =SUM(N85:N87) -> 0 | O88: =SUM(O85:O87) -> 0 | P88: =SUM(P85:P87) -> 0 | Q88: =SUM(Q85:Q87) -> 0 | ... AK88: =SUM(AK85:AK87) -> 0 | AM88: =SUM(AM85:AM87) -> 0 | AN88: =SUM(AN85:AN87) -> 2726595.3
J91: 0 | AK91: Cash Check | AL91: =AN61+AP64+AO64+AN64+AN72-AN88-AO88 -> -2726595.3 | AM91: v | AN91: ='Development Proforma'!I121 -> 761078.99 | AO91: =AL91-AN91 -> -3487674.3
AK92: Profit check | AL92: =AL91+AN87 -> -1965516.3 | AM92: v | AN92: ='Development Proforma'!I119 -> 1522158 | AO92: =AL92-AN92 -> -3487674.3
J94: =-('Development Proforma'!I100) -> -1665691.8 | K94: 0 | L94: 0 | M94: 0 | N94: 0 | O94: 0 | P94: 0 | Q94: 0 | R94: 0 | S94: 0 | T94: 0 | U94: 0 | V94: 0 | W94: 0 | X94: 0 | Y94: 0 | Z94: 0 | AA94: 0 | AB94: 0 | AC94: 0 | AD94: ='Development Proforma'!I120+'Development Proforma'!I117+'Development Proforma'!I100 -> 2648863
E99: =XIRR(J94:AD94,J11:AD11,) -> 0.32173514

Sheet Sales Detail
A1: FIFTH AVENUE - SALES DETAILS
B2: PROJECT: | C2: ='Development Proforma'!C2 -> Seseh Project | G2: TYPE: | H2: Residential | R2: Second Option
B3: ADDRESS: | C3: Coronation Ave, Kelowna | G3: Project #: | H3: ='Development Proforma'!H3 -> TBD
R4: Monthly Payments | S4: =(75/11)/100 -> 0.068181818
B5: ASSUMPTIONS
C7: Pre-sales | D7: ='Inputs & Assumptions'!C27 -> 0.65
C8: Deposit | D8: ='Inputs & Assumptions'!C28 -> 0.15 | F8: Construction Start (10%) | H8: 0.1
C9: Pre-Sales Period | D9: 5 | E9: Months | F9: Monthly Payments (6.8%) | H9: =S4 -> 0.068181818
C10: Commissions | D10: ='Inputs & Assumptions'!C18 -> 0.05
C11: Discounted | D11: 0.93
J12: 1 | K12: 2 | L12: 3 | M12: 4 | N12: 5 | O12: 6 | P12: 7 | Q12: 8 | R12: 9 | S12: 10 | T12: 11 | U12: 12 | V12: 13 | W12: 14 | X12: 15 | Y12: 16 | Z12: 17 | AA12: 18 | AB12: 19 | AC12: 20 | AD12: 21 | AE12: 22 | AF12: 23 | AG12: 24 | AH12: 25 | AI12: 26 | AJ12: 27 | AK12: 28 | AL12: 29 | AM12: 30 | AN12: 31 | AO12: 32 | AP12: 33 | AQ12: 34 | AR12: 35 | AS12: 36 | AU12: Total | AW12: Check
J13: ='Cash Flow'!J11 -> 46054 | K13: ='Cash Flow'!K11 -> 46082 | L13: ='Cash Flow'!L11 -> 46113 | M13: ='Cash Flow'!M11 -> 46143 | N13: ='Cash Flow'!N11 -> 46174 | O13: ='Cash Flow'!O11 -> 46204 | P13: ='Cash Flow'!P11 -> 46235 | Q13: ='Cash Flow'!Q11 -> 46266 | ... AS13: ='Cash Flow'!AS11 -> 47119
B14: SALE PLAN
B16: Percentage | D16: 65% of pre sales done before construction | K16: ='Development Proforma'!I96 -> 2830587.4 | AI16: 0 | AJ16: 0 | AK16: 0.1 | AL16: 0.1 | AM16: 0.1
B17: Contract Value | D17: Recognised on completion | AI17: =AI16*$E$31 -> 0 | AJ17: =AJ16*$E$31 -> 0 | AK17: =AK16*$E$31 -> 0 | AL17: =AL16*$E$31 -> 0 | AM17: =AM16*$E$31 -> 0
B18: Comissions | M18: =M19*M22 -> 21229.405 | N18: =N19*N22 -> 14152.937 | O18: =O19*O22 -> 9649.7296 | P18: =P19*P22 -> 9649.7296 | Q18: =Q19*Q22 -> 9649.7296 | R18: =R19*R22 -> 9649.7296 | S18: =S19*S22 -> 9649.7296 | T18: =T19*T22 -> 9649.7296 | ... Y18: =Y19*Y22 -> 9649.7296
B19: Deposits | D19: 15% of Pre-sale | M19: =K16*D8 -> 424588.1 | N19: =K16*H8 -> 283058.74 | O19: =$K$16*$S$4 -> 192994.59 | P19: =$K$16*$S$4 -> 192994.59 | Q19: =$K$16*$S$4 -> 192994.59 | R19: =$K$16*$S$4 -> 192994.59 | S19: =$K$16*$S$4 -> 192994.59 | T19: =$K$16*$S$4 -> 192994.59 | U19: =$K$16*$S$4 -> 192994.59 | V19: =$K$16*$S$4 -> 192994.59 | ... Y19: =$K$16*$S$4 -> 192994.59 | AI19: =$E$31*AI16*$D$8 -> 0 | AJ19: =$E$31*AJ16*$D$8 -> 0 | AK19: =$E$31*AK16*$D$8 -> 0 | AL19: =$E$31*AL16*$D$8 -> 0 | AM19: =$E$31*AM16*$D$8 -> 0
B20: Revenue Recognition | K20: =SUM(M20:Y20) -> 2689058 | M20: =M19-M18 -> 403358.7 | N20: =N19-N18 -> 268905.8 | O20: =O19-O18 -> 183344.86 | P20: =P19-P18 -> 183344.86 | Q20: =Q19-Q18 -> 183344.86 | R20: =R19-R18 -> 183344.86 | S20: =S19-S18 -> 183344.86 | T20: =T19-T18 -> 183344.86 | ... Y20: =Y19-Y18 -> 183344.86
B22: Commissions (percentage) | M22: =$D$10 -> 0.05 | N22: =$D$10 -> 0.05 | O22: =$D$10 -> 0.05 | P22: =$D$10 -> 0.05 | Q22: =$D$10 -> 0.05 | R22: =$D$10 -> 0.05 | S22: =$D$10 -> 0.05 | T22: =$D$10 -> 0.05 | ... Y22: =$D$10 -> 0.05 | AI22: =$E$31*AI16*$D$10 -> 0 | AJ22: =$E$31*AJ16*$D$10 -> 0 | AK22: =$E$31*AK16*$D$10 -> 0 | AL22: =$E$31*AL16*$D$10 -> 0 | AM22: =$E$31*AM16*$D$10 -> 0
A25: {='Cash Flow'!H6:X63} -> #VALUE!
C34: Unit Mix | D34: Number of units | E34: Unit Sqr m | F34: Total Sqr m | G34: price per sqr m | H34: price per unit | I34: Total Revenue
C35: 2 bedrooms | D35: 13 | E35: 180 | F35: =E35*D35 -> 2340 | G35: =H35/E35 -> 1638.8889 | H35: 295000 | I35: =H35*D35 -> 3835000
C36: 3 bedrooms | D36: 4 | E36: 180 | F36: =E36*D36 -> 720 | G36: =H36/E36 -> 1944.4444 | H36: 350000 | I36: =H36*D36 -> 1400000
C37: 4 bedrooms | D37: 3 | E37: 210 | F37: =E37*D37 -> 630 | G37: =H37/E37 -> 1880.9524 | H37: 395000 | I37: =H37*D37 -> 1185000
C39: Total | D39: =SUM(D35:D37) -> 20 | F39: =SUM(F35:F37) -> 3690 | I39: =SUM(I35:I37) -> 6420000
